aletheia_quantum_genetic_optimizers/__init__.py
aletheia_quantum_genetic_optimizers/bounds/__init__.py
aletheia_quantum_genetic_optimizers/genetic_optimizer/__init__.py
aletheia_quantum_genetic_optimizers/individuals/__init__.py
aletheia_quantum_genetic_optimizers/mutation_methods/__init__.py
aletheia_quantum_genetic_optimizers/population_methods/__init__.py
aletheia_quantum_genetic_optimizers/quantum_technology/__init__.py
aletheia_quantum_genetic_optimizers/reproduction_methods/__init__.py
aletheia_quantum_genetic_optimizers/tournament_methods/__init__.py
aletheia_quantum_genetic_optimizers/variability_explossion_methods/__init__.py
aqgo-0.1.12.dist-info/licenses/LICENSE
aqgo-0.1.12.dist-info/METADATA
aqgo-0.1.12.dist-info/WHEEL
aqgo-0.1.12.dist-info/top_level.txt
aqgo-0.1.12.dist-info/RECORD
