Metadata-Version: 2.4
Name: aqgo
Version: 0.1.12
Summary: Es el optimizador cuántico de AletheIA
Author-email: Luciano Ezequiel Bizin <lucianobizin@gmail.com>, Daniel Sarabia Torres <dsarabiatorres@gmail.com>
License-Expression: MIT
Requires-Python: >=3.10
License-File: LICENSE
Requires-Dist: annotated-types==0.7.0
Requires-Dist: backports.tarfile==1.2.0
Requires-Dist: certifi==2025.1.31
Requires-Dist: cffi==1.17.1
Requires-Dist: charset-normalizer==3.4.1
Requires-Dist: colorama==0.4.6
Requires-Dist: constants_and_tools==0.3.0
Requires-Dist: contourpy==1.3.1
Requires-Dist: cryptography==44.0.2
Requires-Dist: cycler==0.12.1
Requires-Dist: dill==0.3.9
Requires-Dist: docplex==2.29.241
Requires-Dist: docutils==0.21.2
Requires-Dist: et_xmlfile==2.0.0
Requires-Dist: fonttools==4.56.0
Requires-Dist: ibm-cloud-sdk-core==3.23.0
Requires-Dist: ibm-platform-services==0.63.0
Requires-Dist: id==1.5.0
Requires-Dist: idna==3.10
Requires-Dist: importlib_metadata==8.6.1
Requires-Dist: jaraco.classes==3.4.0
Requires-Dist: jaraco.context==6.0.1
Requires-Dist: jaraco.functools==4.1.0
Requires-Dist: joblib==1.4.2
Requires-Dist: keyring==25.6.0
Requires-Dist: kiwisolver==1.4.8
Requires-Dist: lightgbm==4.6.0
Requires-Dist: markdown-it-py==3.0.0
Requires-Dist: matplotlib==3.10.1
Requires-Dist: mdurl==0.1.2
Requires-Dist: more-itertools==10.6.0
Requires-Dist: mpmath==1.3.0
Requires-Dist: narwhals==1.32.0
Requires-Dist: networkx==3.4.2
Requires-Dist: nh3==0.2.21
Requires-Dist: numpy==2.2.3
Requires-Dist: openpyxl==3.1.5
Requires-Dist: packaging==24.2
Requires-Dist: pandas==2.2.3
Requires-Dist: pbr==6.1.1
Requires-Dist: pillow==11.1.0
Requires-Dist: plotly==6.0.1
Requires-Dist: psutil==7.0.0
Requires-Dist: pyarrow==19.0.1
Requires-Dist: pycparser==2.22
Requires-Dist: pydantic==2.9.2
Requires-Dist: pydantic_core==2.23.4
Requires-Dist: pygame==2.6.1
Requires-Dist: Pygments==2.19.1
Requires-Dist: PyJWT==2.10.1
Requires-Dist: pylatexenc==2.10
Requires-Dist: pyparsing==3.2.3
Requires-Dist: pyspnego==0.11.2
Requires-Dist: python-dateutil==2.9.0.post0
Requires-Dist: pytz==2025.1
Requires-Dist: pywin32-ctypes==0.2.3
Requires-Dist: qiskit==1.4.0
Requires-Dist: qiskit-aer==0.16.3
Requires-Dist: qiskit-algorithms==0.3.1
Requires-Dist: qiskit-ibm-runtime==0.36.1
Requires-Dist: qiskit-optimization==0.6.1
Requires-Dist: readme_renderer==44.0
Requires-Dist: requests==2.32.3
Requires-Dist: requests-toolbelt==1.0.0
Requires-Dist: requests_ntlm==1.3.0
Requires-Dist: rfc3986==2.0.0
Requires-Dist: rich==13.9.4
Requires-Dist: rustworkx==0.16.0
Requires-Dist: scikit-learn==1.6.1
Requires-Dist: scipy==1.15.2
Requires-Dist: six==1.17.0
Requires-Dist: sspilib==0.2.0
Requires-Dist: stevedore==5.4.1
Requires-Dist: symengine==0.13.0
Requires-Dist: sympy==1.13.3
Requires-Dist: tabulate==0.9.0
Requires-Dist: threadpoolctl==3.6.0
Requires-Dist: twine==6.1.0
Requires-Dist: typing_extensions==4.13.0
Requires-Dist: tzdata==2025.1
Requires-Dist: urllib3==2.3.0
Requires-Dist: websocket-client==1.8.0
Requires-Dist: zipp==3.21.0
Dynamic: license-file
